telemetrix_lite/__init__.py
telemetrix_lite/rfid_pn532.py
telemetrix_lite/telemetrix_sync.py
telemetrix_lite-0.1.0.dist-info/licenses/LICENSE
telemetrix_lite-0.1.0.dist-info/METADATA
telemetrix_lite-0.1.0.dist-info/WHEEL
telemetrix_lite-0.1.0.dist-info/top_level.txt
telemetrix_lite-0.1.0.dist-info/RECORD
