Metadata-Version: 2.4
Name: telemetrix-lite
Version: 0.1.0
Summary: Lite, teacher-friendly wrapper for Telemetrix (digital/analog/sonar/LCD) + RFID helpers (PN532 UART, RC522 bridge).
Author-email: Barmaja Robotics School <team@barmaja.school>
License: MIT License
Project-URL: Homepage, https://github.com/barmaja-school/telemetrix-lite
Project-URL: Source, https://github.com/barmaja-school/telemetrix-lite
Project-URL: Issues, https://github.com/barmaja-school/telemetrix-lite/issues
Classifier: Programming Language :: Python :: 3
Classifier: License :: OSI Approved :: MIT License
Classifier: Operating System :: OS Independent
Classifier: Topic :: Education
Classifier: Topic :: System :: Hardware :: Hardware Drivers
Requires-Python: >=3.8
License-File: LICENSE
Requires-Dist: telemetrix>=1.16.0
Requires-Dist: pyserial>=3.5
Dynamic: license-file
